{
  "date": "2026-07-24",
  "generated_at_kst": "2026-07-24T08:20:00+09:00",
  "mode": "new",
  "headline": "코스피, 3거래일 연속 상승 속 7,096.89(+4.40%)로 7000선 회복—알파벳 실적 후 AI/메모리 수요 기대에 반도체·바이오·2차전지 동반 급등, 코스닥은 올해 14번째 매수 사이드카 발동(+5.22%). 그러나 밤사이 미국은 정반대로 급락—중동 확전에 국제유가 100달러 돌파 + 알파벳·테슬라 실적발 AI capex 우려 겹치며 나스닥 -2.15%(6월23일 이후 최악의 하루)",

  "kr": {
    "preview": "23일 코스피는 전 거래일보다 299.19포인트(+4.40%) 오른 7,096.89로 마감, 3거래일 연속 상승하며 7,000선을 재탈환했다. 장 초반 6,900선까지 밀렸으나 알파벳의 AI 데이터센터 투자 확대 발표(정규장 마감 후 실적 발표) 여파로 메모리 반도체 수요 기대감이 살아나며 외국인이 2조1,351억원(코스피)·1,330억원(코스닥) 순매수로 전환, 지수를 끌어올렸다. 삼성전자는 +3.65%(27만원), SK하이닉스는 +4.86%(191만9,000원)를 기록했다. 코스닥은 +5.22%(790.28) 급등하며 오후 2시27분 올해 14번째 매수 사이드카가 발동됐는데, 알테오젠(+14.37%) 등 바이오주와 에코프로비엠(+9.95%)·에코프로(+9.34%) 등 2차전지주가 상승을 주도했다. 업종별로는 건설(+10.5%)이 가장 강했고 IT서비스(+7.8%), 금속(+7.2%), 화학(+6.4%)이 뒤를 이었다. 원/달러 환율은 13.3원 내린 1,466.8원으로 안정세를 보였다.",
    "indices": [
      { "name": "코스피", "value": "7,096.89", "change_pct": "+4.40%" },
      { "name": "코스닥", "value": "790.28", "change_pct": "+5.22%" }
    ],
    "hot_stocks": [
      {
        "ticker": "005930",
        "name": "삼성전자",
        "change_pct": "+3.65%",
        "reason": "23일 27만원 마감. 알파벳이 정규장 마감 후 실적 발표에서 AI 데이터센터 투자 확대 계획을 밝히며 메모리 반도체(HBM 등) 수요 기대감이 부각, 외국인 순매수(코스피 +2조1,351억원)가 유입되며 반도체 대형주 강세를 이끌었다.",
        "source_url": "https://www.hankyung.com/article/2026072322466"
      },
      {
        "ticker": "000660",
        "name": "SK하이닉스",
        "change_pct": "+4.86%",
        "reason": "23일 191만9,000원 마감. 삼성전자와 함께 알파벳發 AI/메모리 수요 기대감에 강세, 외국인 매수세가 반도체 업종 전반에 집중됐다.",
        "source_url": "https://www.fnnews.com/news/202607231603513186"
      },
      {
        "ticker": "196170",
        "name": "알테오젠",
        "change_pct": "+14.37%",
        "reason": "23일 30만6,500원 마감. 바이오 업종 전반의 강세 속 코스닥 시가총액 상위 종목으로 부각, 히알루로니다제 원천기술 기반 기술수출 기대감이 지속되며 코스닥 급등(+5.22%, 매수 사이드카 발동)을 주도했다.",
        "source_url": "https://www.hankyung.com/article/2026072322466"
      },
      {
        "ticker": "247540",
        "name": "에코프로비엠",
        "change_pct": "+9.95%",
        "reason": "23일 마감. 2차전지 고객사 재고조정 마무리에 따른 판매량 반등 기대와 리튬 등 메탈 가격 상승세가 반영되며 에코프로(+9.34%)와 함께 그룹주 동반 급등.",
        "source_url": "https://www.cbci.co.kr/news/articleView.html?idxno=590999"
      },
      {
        "ticker": "277810",
        "name": "레인보우로보틱스",
        "change_pct": "+6.17%",
        "reason": "23일 마감. 전일(22일) 최대주주 삼성전자의 로봇사업조직(RX) 신설 소식에 따른 로봇 테마 강세가 이어지며 추가 상승.",
        "source_url": "https://www.hankyung.com/article/2026072322466"
      }
    ]
  },

  "us": {
    "recap": "23일(현지시간) 뉴욕증시는 3대 지수가 동반 급락했다. 다우존스는 506.93포인트(-0.97%) 내린 51,711.65, S&P500은 90.66포인트(-1.21%) 내린 7,408.30, 나스닥은 553.21포인트(-2.15%) 내린 25,137.69로 마감했다—나스닥·S&P 모두 6월23일 이후 최악의 하루. 전일 정규장 마감 후 발표된 알파벳(-7%)과 테슬라(-14.5%, 2분기 잉여현금흐름 악화)의 실적이 AI 자본지출 우려를 촉발했고, 여기에 예멘 후티 반군의 사우디 유조선 공격 소식으로 브렌트유가 배럴당 100달러를 돌파(두 달 만)하며 인플레이션 재점화 우려가 겹쳤다. 미 10년물 국채금리는 4.71%까지 급등해 2025년 초 이후 최고치를 기록했다. 통신서비스 섹터가 -5.2%로 가장 부진했고, 록히드마틴(+10.5%, 실적 호조·가이던스 상향)·RTX(+7.3%)·서모피셔(+8.7%) 등은 강세를 보였다.",
    "indices": [
      { "name": "S&P 500", "value": "7,408.30", "change_pct": "-1.21%" },
      { "name": "나스닥", "value": "25,137.69", "change_pct": "-2.15%" },
      { "name": "다우", "value": "51,711.65", "change_pct": "-0.97%" }
    ],
    "notable": [
      {
        "ticker": "GOOGL",
        "name": "알파벳",
        "change_pct": "-7%",
        "reason": "2분기 매출은 컨센서스를 상회했으나 AI 데이터센터 투자 확대에 따른 자본지출 증가와 현금 소진 우려로 급락, 통신서비스 섹터 하락(-5.2%)의 주요 원인이 됐다.",
        "source_url": "https://www.cnbc.com/2026/07/23/tesla-tsla-alphabet-googl-stock-today.html"
      },
      {
        "ticker": "TSLA",
        "name": "테슬라",
        "change_pct": "-14.5%",
        "reason": "2분기 잉여현금흐름 악화 등 실적 부진에 급락, 소비재 섹터(XLY) 전반의 약세를 주도했다(XLY 내 비중 약 19%).",
        "source_url": "https://www.cnbc.com/2026/07/23/tesla-tsla-alphabet-googl-stock-today.html"
      },
      {
        "ticker": "LMT",
        "name": "록히드마틴",
        "change_pct": "+10.5%",
        "reason": "2026년 실적 가이던스 상향 발표에 급등, 산업재 섹터(+1.61%) 강세를 이끌었다.",
        "source_url": "https://www.staradvertiser.com/2026/07/23/breaking-news/wall-street-slides-after-alphabet-tesla-revive-ai-spending-fears/"
      }
    ]
  },

  "sectors": {
    "kr": [
      { "name": "반도체", "change_pct": "+4.3%", "note": "(대표종목 기준: 삼성전자 +3.65%, SK하이닉스 +4.86%) 알파벳發 AI/메모리 수요 기대" },
      { "name": "IT/기술", "change_pct": "+7.8%", "note": "KRX IT서비스 업종지수" },
      { "name": "통신", "change_pct": "미확인", "note": "" },
      { "name": "바이오/제약", "change_pct": "+9.0%", "note": "(대표종목 기준: 알테오젠 +14.37% 등 바이오주 동반 강세)" },
      { "name": "금융", "change_pct": "미확인", "note": "" },
      { "name": "유통/소비재", "change_pct": "미확인", "note": "유통주(이마트·롯데쇼핑 등) 개별 강세 소식은 있으나 업종지수 확인 안됨" },
      { "name": "자동차", "change_pct": "미확인", "note": "기아 -0.24% 외 뚜렷한 업종 수치 확인 안됨" },
      { "name": "2차전지", "change_pct": "+9.6%", "note": "(대표종목 기준: 에코프로비엠 +9.95%, 에코프로 +9.34%)" },
      { "name": "조선/방산", "change_pct": "+1.0%", "note": "(대표종목 기준: HD현대중공업 +1.86%, 한화에어로스페이스 +0.08%)" },
      { "name": "건설", "change_pct": "+10.5%", "note": "KRX 건설업종지수" },
      { "name": "화학/소재", "change_pct": "+6.4%", "note": "KRX 화학업종지수" },
      { "name": "철강/금속", "change_pct": "+7.2%", "note": "KRX 금속업종지수" },
      { "name": "인터넷/게임", "change_pct": "미확인", "note": "네이버 -2.30% vs 일부 게임주 강세로 업종 방향성 혼조" },
      { "name": "엔터/미디어", "change_pct": "미확인", "note": "한한령 해제 기대에 화장품·엔터 개별 종목 강세 소식은 있으나 업종지수 확인 안됨" }
    ],
    "us": [
      { "name": "반도체", "change_pct": "-3%", "note": "(대표종목 기준: 텍사스인스트루먼트 -3%) AI 자본지출 우려" },
      { "name": "기술(빅테크)", "change_pct": "미확인", "note": "" },
      { "name": "통신서비스", "change_pct": "-5.2%", "note": "알파벳 -7%가 지수 견인, 최대 낙폭 섹터" },
      { "name": "헬스케어", "change_pct": "미확인", "note": "" },
      { "name": "금융", "change_pct": "미확인", "note": "" },
      { "name": "경기소비재", "change_pct": "-4%", "note": "(대표종목 기준: 테슬라 -14.5%, 아마존 -4.5%)" },
      { "name": "필수소비재", "change_pct": "미확인", "note": "" },
      { "name": "산업재", "change_pct": "+1.61%", "note": "록히드마틴 +10.5%, RTX +7.3%가 견인" },
      { "name": "소재", "change_pct": "-1.07%", "note": "" },
      { "name": "에너지", "change_pct": "+0.98%", "note": "국제유가 급등 수혜" },
      { "name": "유틸리티", "change_pct": "+0.53%", "note": "" },
      { "name": "부동산", "change_pct": "-0.04%", "note": "" }
    ]
  },

  "assets": [
    { "name": "원/달러", "value": "1,466.8", "change_pct": "-0.90%" },
    { "name": "달러인덱스", "value": "101.14", "change_pct": "-0.03%" },
    { "name": "금", "value": "$4,115.89", "change_pct": "+1.0%" },
    { "name": "WTI", "value": "$92.19", "change_pct": "+6.17%" },
    { "name": "비트코인", "value": "$65,047", "change_pct": "-1.56%" },
    { "name": "이더리움", "value": "$1,883.70", "change_pct": "-2.57%" },
    { "name": "미 10년물", "value": "4.71%", "change_pct": "+5.25bp" }
  ],

  "macro": {
    "rates_fx_commodities": "브렌트유가 예멘 후티 반군의 사우디 유조선 공격 소식에 7% 급등, 두 달 만에 배럴당 100달러(종가 기준)를 돌파했다. WTI도 6% 넘게 올라 $92선에 마감. 유가발 인플레이션 재점화 우려로 미 10년물 국채금리는 4.71%까지 뛰며 2025년 초 이후 최고치를 기록했다. 원/달러 환율은 외국인 순매수 전환 속 1,466.8원으로 소폭 안정.",
    "notes": "트럼프 대통령이 \"대규모 (이란) 공격을 검토하고 있다\"고 언급하며 중동 확전 우려가 고조. 호르무즈 해협에 이어 바브엘만데브 해협까지 봉쇄될 경우 전 세계 원유 공급량의 약 25%에 차질이 우려된다는 분석이 나온다."
  },

  "top_themes": [
    {
      "theme": "중동 확전에 국제유가 배럴당 100달러 돌파—두 달 만에 최고치",
      "summary": "예멘 후티 반군의 사우디 유조선 공격 소식에 브렌트유가 7.04% 급등해 $100.69에 마감했고, 트럼프 대통령의 \"대규모 이란 공격 검토\" 발언까지 겹치며 호르무즈·바브엘만데브 해협 통항 차질 우려가 고조됐다. 이 여파로 미 10년물 국채금리는 4.71%까지 급등(2025년 초 이후 최고)했다.",
      "tickers": ["WTI", "BRENT"],
      "source_url": "https://www.fnnews.com/news/202607240509025758"
    },
    {
      "theme": "알파벳·테슬라 실적발 AI 자본지출 우려—美 3대지수 동반 급락",
      "summary": "알파벳(-7%)과 테슬라(-14.5%)가 2분기 실적 발표 후 대규모 capex·현금소진 우려로 급락하며 나스닥 -2.15%(6월23일 이후 최악), S&P500 -1.21%, 다우 -0.97%를 기록했다. 통신서비스 섹터가 -5.2%로 최대 낙폭을 보였다.",
      "tickers": ["GOOGL", "TSLA"],
      "source_url": "https://www.staradvertiser.com/2026/07/23/breaking-news/wall-street-slides-after-alphabet-tesla-revive-ai-spending-fears/"
    },
    {
      "theme": "코스피, 알파벳發 반도체 훈풍에 7000선 회복—외국인 순매수 전환",
      "summary": "알파벳의 AI 데이터센터 투자 확대 시그널이 국내 메모리 반도체 수요 기대로 이어지며 삼성전자·SK하이닉스 등 대형주가 강세를 보였고, 코스피는 3거래일 연속 상승하며 +4.40%(7,096.89)로 마감했다. 외국인이 코스피에서 2조1,351억원 순매수로 전환하며 지수 상승을 견인했다.",
      "tickers": ["005930", "000660"],
      "source_url": "https://www.hankyung.com/article/2026072322466"
    },
    {
      "theme": "코스닥, 올해 14번째 매수 사이드카—바이오·2차전지 동반 급등",
      "summary": "코스닥이 장중 급등하며 올해 14번째 매수 사이드카가 발동(오후 2시27분)됐다. 알테오젠(+14.37%)을 비롯한 바이오주와 에코프로비엠(+9.95%)·에코프로(+9.34%) 등 2차전지주가 지수 상승을 주도했으며 외국인·기관이 동반 순매수했다.",
      "tickers": ["196170", "247540", "086520"],
      "source_url": "https://www.hankyung.com/article/2026072322466"
    },
    {
      "theme": "건설·화학·금속 업종 급등—경기민감주 전반 강세",
      "summary": "코스피 업종별로는 건설(+10.5%)이 가장 강한 상승률을 보였고 IT서비스(+7.8%), 금속(+7.2%), 화학(+6.4%)이 뒤를 이으며 경기민감 업종 전반에 매수세가 유입됐다.",
      "tickers": [],
      "source_url": "https://www.hellot.net/news/article.html?no=113937"
    }
  ],

  "watchlist": [
    { "ticker": "NVDA", "name": "NVIDIA", "market": "US", "news": "$212.06(+1.97%)로 마감, 알파벳·테슬라발 AI capex 우려 속에서도 반도체 대장주로서 상대적으로 견조한 흐름을 보였다.", "source_url": "https://finance.yahoo.com/quote/NVDA/" },
    { "ticker": "AAPL", "name": "Apple", "market": "US", "news": "$325선에서 거래, 이날 등락률은 확인되지 않음.", "source_url": "https://finance.yahoo.com/quote/AAPL/" },
    { "ticker": "MSFT", "name": "Microsoft", "market": "US", "news": "$388.16 기록, 전일 400달러선 하회 이후 약세 흐름이 이어지는 모습.", "source_url": "https://finance.yahoo.com/quote/MSFT/" },
    { "ticker": "TSLA", "name": "Tesla", "market": "US", "news": "2분기 잉여현금흐름 악화 등 실적 미스로 -14.5% 급락, 이날 미국 증시 하락의 최대 요인 중 하나.", "source_url": "https://www.cnbc.com/2026/07/23/tesla-tsla-alphabet-googl-stock-today.html" },
    { "ticker": "PLTR", "name": "Palantir", "market": "US", "news": "규제·밸류에이션 우려 속 약세 흐름이 지속되는 모습이나 이날 정확한 등락률은 확인되지 않음.", "source_url": "https://finance.yahoo.com/quote/PLTR/" },
    { "ticker": "005930", "name": "삼성전자", "market": "KR", "news": "23일 +3.65%(27만원) 마감, 알파벳發 메모리 수요 기대감에 외국인 순매수 유입.", "source_url": "https://www.hankyung.com/article/2026072322466" },
    { "ticker": "000660", "name": "SK하이닉스", "market": "KR", "news": "23일 +4.86%(191만9,000원) 마감, 반도체 대형주 강세를 주도. 2분기 실적발표는 7월29일 예정.", "source_url": "https://www.fnnews.com/news/202607231603513186" },
    { "ticker": "373220", "name": "LG에너지솔루션", "market": "KR", "news": "이날 구체적 등락률은 확인되지 않음. 2차전지 업황 반등 기대감(고객사 재고조정 마무리, 메탈가격 상승)은 유효.", "source_url": "https://www.cbci.co.kr/news/articleView.html?idxno=590999" },
    { "ticker": "005380", "name": "현대차", "market": "KR", "news": "이날 구체적 등락률은 확인되지 않음. 휴머노이드·로보틱스 관련 성장 기대감이 이어지는 업종 분위기 속 흐름을 지켜볼 필요.", "source_url": "https://www.hankyung.com/article/2026072322466" }
  ],

  "spotlight": [
    {
      "ticker": "000660",
      "name": "SK하이닉스",
      "market": "KR",
      "thesis": "알파벳의 AI 데이터센터 투자 확대 시그널로 메모리(HBM 포함) 수요 기대감이 재점화되며 23일 +4.86% 강세. 2분기 실적발표(7월29일)를 앞두고 컨센서스(매출 83조9,264억원, 영업이익 64조1,632억원, 영업이익률 76.5% 사상 최고 전망)에 시장의 관심이 집중되고 있다.",
      "catalysts": ["2분기 실적발표 (2026-07-29)", "美 빅테크 AI 데이터센터 투자 동향"],
      "levels_watched": {
        "support": "미확인",
        "resistance": "미확인",
        "analyst_target_cited": "KB증권 420만원(2026-07-09) — 단, 증권가 목표주가는 185만~420만원까지 크게 엇갈림(AI 투자 지속가능성에 대한 해석 차이)"
      },
      "risk": "美 빅테크의 AI 투자 지속가능성에 대한 우려가 재부각될 경우(알파벳·테슬라 사례처럼) 밸류에이션 조정 가능성. 목표주가 편차가 커 불확실성이 높음.",
      "sources": ["https://www.investchosun.com/site/data/html_dir/2026/07/09/2026070980118.html", "https://www.fnnews.com/news/202607231603513186"]
    },
    {
      "ticker": "196170",
      "name": "알테오젠",
      "market": "KR",
      "thesis": "23일 +14.37%(30만6,500원)로 코스닥 시가총액 상위 종목 중 최대 상승폭을 기록하며 코스닥 매수 사이드카 발동을 견인. 히알루로니다제 원천기술(ALT-B4) 기반 글로벌 제약사 기술수출 확대 기대감이 바이오 업종 전반 강세와 맞물렸다.",
      "catalysts": ["글로벌 제약사와의 추가 기술이전 계약 가능성", "코스닥 바이오 업종 자금 유입 지속 여부"],
      "levels_watched": {
        "support": "미확인",
        "resistance": "미확인",
        "analyst_target_cited": "미확인"
      },
      "risk": "단기 급등에 따른 차익실현 매물 출회 가능성, 기술수출 관련 뉴스가 구체화되지 않을 경우 변동성 확대 우려.",
      "sources": ["https://www.hankyung.com/article/2026072322466"]
    }
  ],

  "disclaimer": "⚠️ 본 브리핑은 공개된 뉴스·시장 데이터를 정리한 정보 제공용 자료이며, 투자 권유나 특정 종목 매수·매도 추천이 아닙니다. 모든 투자 판단과 책임은 본인에게 있습니다. 인용된 목표가·전망은 각 출처의 의견입니다."
}
